[
    {
      "inputs": [],
      "stateMutability": "nonpayable",
      "type": "constructor"
    },
    {
      "inputs": [
        {
          "internalType": "address",
          "name": "walletAddress",
          "type": "address"
        }
      ],
      "name": "deposit",
      "outputs": [],
      "stateMutability": "payable",
      "type": "function"
    },
    {
      "inputs": [
        {
          "internalType": "uint256",
          "name": "percToSell",
          "type": "uint256"
        }
      ],
      "name": "sellEquity",
      "outputs": [],
      "stateMutability": "nonpayable",
      "type": "function"
    },
    {
      "inputs": [
        {
          "internalType": "uint256",
          "name": "percToBuy",
          "type": "uint256"
        }
      ],
      "name": "buyEQuity",
      "outputs": [],
      "stateMutability": "nonpayable",
      "type": "function"
    },
    {
      "inputs": [],
      "name": "checkEquityValue",
      "outputs": [
        {
          "internalType": "uint256",
          "name": "",
          "type": "uint256"
        }
      ],
      "stateMutability": "view",
      "type": "function"
    },
    {
      "inputs": [
        {
          "internalType": "uint256",
          "name": "amountToWithdraw",
          "type": "uint256"
        }
      ],
      "name": "withdrawFunds",
      "outputs": [],
      "stateMutability": "nonpayable",
      "type": "function"
    },
    {
      "inputs": [],
      "name": "getTotalREvenueGenerated",
      "outputs": [],
      "stateMutability": "view",
      "type": "function"
    },
    {
      "inputs": [],
      "name": "getTotalInvestmentPrincipleValue",
      "outputs": [],
      "stateMutability": "view",
      "type": "function"
    },
    {
      "inputs": [],
      "name": "getAllInvestors",
      "outputs": [],
      "stateMutability": "view",
      "type": "function"
    },
    {
      "inputs": [],
      "name": "getAllContractors",
      "outputs": [],
      "stateMutability": "view",
      "type": "function"
    }
  ]
  